{
  "apps/cms-api": {
    "root": [
      "apps/cms-api/project.json",
      "nx/core/project-json"
    ],
    "targets": [
      "apps/cms-api/tsconfig.json",
      "@nx/js/typescript"
    ],
    "targets.typecheck": [
      "apps/cms-api/tsconfig.json",
      "@nx/js/typescript"
    ],
    "targets.typecheck.dependsOn": [
      "apps/cms-api/tsconfig.json",
      "@nx/js/typescript"
    ],
    "targets.typecheck.options": [
      "apps/cms-api/tsconfig.json",
      "@nx/js/typescript"
    ],
    "targets.typecheck.cache": [
      "apps/cms-api/tsconfig.json",
      "@nx/js/typescript"
    ],
    "targets.typecheck.inputs": [
      "apps/cms-api/tsconfig.json",
      "@nx/js/typescript"
    ],
    "targets.typecheck.outputs": [
      "apps/cms-api/tsconfig.json",
      "@nx/js/typescript"
    ],
    "targets.typecheck.syncGenerators": [
      "apps/cms-api/tsconfig.json",
      "@nx/js/typescript"
    ],
    "targets.typecheck.metadata": [
      "apps/cms-api/tsconfig.json",
      "@nx/js/typescript"
    ],
    "targets.typecheck.executor": [
      "apps/cms-api/tsconfig.json",
      "@nx/js/typescript"
    ],
    "targets.typecheck.options.cwd": [
      "apps/cms-api/tsconfig.json",
      "@nx/js/typescript"
    ],
    "targets.typecheck.options.command": [
      "apps/cms-api/tsconfig.json",
      "@nx/js/typescript"
    ],
    "targets.typecheck.metadata.technologies": [
      "apps/cms-api/tsconfig.json",
      "@nx/js/typescript"
    ],
    "targets.typecheck.metadata.technologies.0": [
      "apps/cms-api/tsconfig.json",
      "@nx/js/typescript"
    ],
    "targets.typecheck.metadata.description": [
      "apps/cms-api/tsconfig.json",
      "@nx/js/typescript"
    ],
    "targets.typecheck.metadata.help": [
      "apps/cms-api/tsconfig.json",
      "@nx/js/typescript"
    ],
    "targets.typecheck.metadata.help.command": [
      "apps/cms-api/tsconfig.json",
      "@nx/js/typescript"
    ],
    "targets.typecheck.metadata.help.example": [
      "apps/cms-api/tsconfig.json",
      "@nx/js/typescript"
    ],
    "targets.test": [
      "apps/cms-api/jest.config.ts",
      "@nx/jest/plugin"
    ],
    "targets.test.options": [
      "apps/cms-api/jest.config.ts",
      "@nx/jest/plugin"
    ],
    "targets.test.metadata": [
      "apps/cms-api/jest.config.ts",
      "@nx/jest/plugin"
    ],
    "targets.test.cache": [
      "apps/cms-api/jest.config.ts",
      "@nx/jest/plugin"
    ],
    "targets.test.inputs": [
      "apps/cms-api/jest.config.ts",
      "@nx/jest/plugin"
    ],
    "targets.test.outputs": [
      "apps/cms-api/jest.config.ts",
      "@nx/jest/plugin"
    ],
    "targets.test.executor": [
      "apps/cms-api/jest.config.ts",
      "@nx/jest/plugin"
    ],
    "targets.test.options.cwd": [
      "apps/cms-api/jest.config.ts",
      "@nx/jest/plugin"
    ],
    "targets.test.options.env": [
      "apps/cms-api/jest.config.ts",
      "@nx/jest/plugin"
    ],
    "targets.test.options.command": [
      "apps/cms-api/jest.config.ts",
      "@nx/jest/plugin"
    ],
    "targets.test.metadata.technologies": [
      "apps/cms-api/jest.config.ts",
      "@nx/jest/plugin"
    ],
    "targets.test.metadata.technologies.0": [
      "apps/cms-api/jest.config.ts",
      "@nx/jest/plugin"
    ],
    "targets.test.metadata.description": [
      "apps/cms-api/jest.config.ts",
      "@nx/jest/plugin"
    ],
    "targets.test.metadata.help": [
      "apps/cms-api/jest.config.ts",
      "@nx/jest/plugin"
    ],
    "targets.test.metadata.help.command": [
      "apps/cms-api/jest.config.ts",
      "@nx/jest/plugin"
    ],
    "targets.test.metadata.help.example": [
      "apps/cms-api/jest.config.ts",
      "@nx/jest/plugin"
    ],
    "name": [
      "apps/cms-api/project.json",
      "nx/core/project-json"
    ],
    "$schema": [
      "apps/cms-api/project.json",
      "nx/core/project-json"
    ],
    "sourceRoot": [
      "apps/cms-api/project.json",
      "nx/core/project-json"
    ],
    "projectType": [
      "apps/cms-api/project.json",
      "nx/core/project-json"
    ],
    "tags": [
      "apps/cms-api/project.json",
      "nx/core/project-json"
    ],
    "tags.scope:api": [
      "apps/cms-api/project.json",
      "nx/core/project-json"
    ],
    "tags.type:backend": [
      "apps/cms-api/project.json",
      "nx/core/project-json"
    ],
    "targets.build": [
      "apps/cms-api/project.json",
      "nx/core/project-json"
    ],
    "targets.build.executor": [
      "apps/cms-api/project.json",
      "nx/core/project-json"
    ],
    "targets.build.outputs": [
      "apps/cms-api/project.json",
      "nx/core/project-json"
    ],
    "targets.build.options": [
      "apps/cms-api/project.json",
      "nx/core/project-json"
    ],
    "targets.build.options.outputPath": [
      "apps/cms-api/project.json",
      "nx/core/project-json"
    ],
    "targets.build.options.main": [
      "apps/cms-api/project.json",
      "nx/core/project-json"
    ],
    "targets.build.options.tsConfig": [
      "apps/cms-api/project.json",
      "nx/core/project-json"
    ],
    "targets.build.options.assets": [
      "apps/cms-api/project.json",
      "nx/core/project-json"
    ],
    "targets.serve": [
      "apps/cms-api/project.json",
      "nx/core/project-json"
    ],
    "targets.serve.executor": [
      "apps/cms-api/project.json",
      "nx/core/project-json"
    ],
    "targets.serve.options": [
      "apps/cms-api/project.json",
      "nx/core/project-json"
    ],
    "targets.serve.options.buildTarget": [
      "apps/cms-api/project.json",
      "nx/core/project-json"
    ],
    "targets.serve:dev": [
      "apps/cms-api/project.json",
      "nx/core/project-json"
    ],
    "targets.serve:dev.executor": [
      "apps/cms-api/project.json",
      "nx/core/project-json"
    ],
    "targets.serve:dev.options": [
      "apps/cms-api/project.json",
      "nx/core/project-json"
    ],
    "targets.serve:dev.options.command": [
      "apps/cms-api/project.json",
      "nx/core/project-json"
    ],
    "targets.lint": [
      "apps/cms-api/project.json",
      "nx/core/project-json"
    ],
    "targets.lint.executor": [
      "apps/cms-api/project.json",
      "nx/core/project-json"
    ],
    "targets.test.dependsOn": [
      "nx.json",
      "nx/target-defaults"
    ],
    "targets.test.parallelism": [
      "nx.json",
      "nx/target-defaults"
    ]
  },
  "packages/cms/ui": {
    "root": [
      "packages/cms/ui/package.json",
      "nx/core/package-json"
    ],
    "targets": [
      "packages/cms/ui/tsconfig.json",
      "@nx/js/typescript"
    ],
    "targets.typecheck": [
      "packages/cms/ui/tsconfig.json",
      "@nx/js/typescript"
    ],
    "targets.typecheck.dependsOn": [
      "packages/cms/ui/tsconfig.json",
      "@nx/js/typescript"
    ],
    "targets.typecheck.options": [
      "packages/cms/ui/tsconfig.json",
      "@nx/js/typescript"
    ],
    "targets.typecheck.cache": [
      "packages/cms/ui/tsconfig.json",
      "@nx/js/typescript"
    ],
    "targets.typecheck.inputs": [
      "packages/cms/ui/tsconfig.json",
      "@nx/js/typescript"
    ],
    "targets.typecheck.outputs": [
      "packages/cms/ui/tsconfig.json",
      "@nx/js/typescript"
    ],
    "targets.typecheck.syncGenerators": [
      "packages/cms/ui/tsconfig.json",
      "@nx/js/typescript"
    ],
    "targets.typecheck.metadata": [
      "packages/cms/ui/tsconfig.json",
      "@nx/js/typescript"
    ],
    "targets.typecheck.executor": [
      "packages/cms/ui/tsconfig.json",
      "@nx/js/typescript"
    ],
    "targets.typecheck.options.cwd": [
      "packages/cms/ui/tsconfig.json",
      "@nx/js/typescript"
    ],
    "targets.typecheck.options.command": [
      "packages/cms/ui/tsconfig.json",
      "@nx/js/typescript"
    ],
    "targets.typecheck.metadata.technologies": [
      "packages/cms/ui/tsconfig.json",
      "@nx/js/typescript"
    ],
    "targets.typecheck.metadata.technologies.0": [
      "packages/cms/ui/tsconfig.json",
      "@nx/js/typescript"
    ],
    "targets.typecheck.metadata.description": [
      "packages/cms/ui/tsconfig.json",
      "@nx/js/typescript"
    ],
    "targets.typecheck.metadata.help": [
      "packages/cms/ui/tsconfig.json",
      "@nx/js/typescript"
    ],
    "targets.typecheck.metadata.help.command": [
      "packages/cms/ui/tsconfig.json",
      "@nx/js/typescript"
    ],
    "targets.typecheck.metadata.help.example": [
      "packages/cms/ui/tsconfig.json",
      "@nx/js/typescript"
    ],
    "targets.lint": [
      "packages/cms/ui/eslint.config.mjs",
      "@nx/eslint/plugin"
    ],
    "targets.lint.cache": [
      "packages/cms/ui/eslint.config.mjs",
      "@nx/eslint/plugin"
    ],
    "targets.lint.options": [
      "packages/cms/ui/eslint.config.mjs",
      "@nx/eslint/plugin"
    ],
    "targets.lint.inputs": [
      "packages/cms/ui/eslint.config.mjs",
      "@nx/eslint/plugin"
    ],
    "targets.lint.outputs": [
      "packages/cms/ui/eslint.config.mjs",
      "@nx/eslint/plugin"
    ],
    "targets.lint.metadata": [
      "packages/cms/ui/eslint.config.mjs",
      "@nx/eslint/plugin"
    ],
    "targets.lint.executor": [
      "packages/cms/ui/eslint.config.mjs",
      "@nx/eslint/plugin"
    ],
    "targets.lint.options.cwd": [
      "packages/cms/ui/eslint.config.mjs",
      "@nx/eslint/plugin"
    ],
    "targets.lint.options.command": [
      "packages/cms/ui/eslint.config.mjs",
      "@nx/eslint/plugin"
    ],
    "targets.lint.metadata.technologies": [
      "packages/cms/ui/eslint.config.mjs",
      "@nx/eslint/plugin"
    ],
    "targets.lint.metadata.technologies.0": [
      "packages/cms/ui/eslint.config.mjs",
      "@nx/eslint/plugin"
    ],
    "targets.lint.metadata.description": [
      "packages/cms/ui/eslint.config.mjs",
      "@nx/eslint/plugin"
    ],
    "targets.lint.metadata.help": [
      "packages/cms/ui/eslint.config.mjs",
      "@nx/eslint/plugin"
    ],
    "targets.lint.metadata.help.command": [
      "packages/cms/ui/eslint.config.mjs",
      "@nx/eslint/plugin"
    ],
    "targets.lint.metadata.help.example": [
      "packages/cms/ui/eslint.config.mjs",
      "@nx/eslint/plugin"
    ],
    "targets.test": [
      "packages/cms/ui/jest.config.ts",
      "@nx/jest/plugin"
    ],
    "targets.test.options": [
      "packages/cms/ui/jest.config.ts",
      "@nx/jest/plugin"
    ],
    "targets.test.metadata": [
      "packages/cms/ui/jest.config.ts",
      "@nx/jest/plugin"
    ],
    "targets.test.cache": [
      "packages/cms/ui/jest.config.ts",
      "@nx/jest/plugin"
    ],
    "targets.test.inputs": [
      "packages/cms/ui/jest.config.ts",
      "@nx/jest/plugin"
    ],
    "targets.test.outputs": [
      "packages/cms/ui/jest.config.ts",
      "@nx/jest/plugin"
    ],
    "targets.test.executor": [
      "packages/cms/ui/jest.config.ts",
      "@nx/jest/plugin"
    ],
    "targets.test.options.cwd": [
      "packages/cms/ui/jest.config.ts",
      "@nx/jest/plugin"
    ],
    "targets.test.options.env": [
      "packages/cms/ui/jest.config.ts",
      "@nx/jest/plugin"
    ],
    "targets.test.options.command": [
      "packages/cms/ui/jest.config.ts",
      "@nx/jest/plugin"
    ],
    "targets.test.metadata.technologies": [
      "packages/cms/ui/jest.config.ts",
      "@nx/jest/plugin"
    ],
    "targets.test.metadata.technologies.0": [
      "packages/cms/ui/jest.config.ts",
      "@nx/jest/plugin"
    ],
    "targets.test.metadata.description": [
      "packages/cms/ui/jest.config.ts",
      "@nx/jest/plugin"
    ],
    "targets.test.metadata.help": [
      "packages/cms/ui/jest.config.ts",
      "@nx/jest/plugin"
    ],
    "targets.test.metadata.help.command": [
      "packages/cms/ui/jest.config.ts",
      "@nx/jest/plugin"
    ],
    "targets.test.metadata.help.example": [
      "packages/cms/ui/jest.config.ts",
      "@nx/jest/plugin"
    ],
    "targets.build": [
      "packages/cms/ui/rollup.config.cjs",
      "@nx/rollup/plugin"
    ],
    "targets.build.options": [
      "packages/cms/ui/rollup.config.cjs",
      "@nx/rollup/plugin"
    ],
    "targets.build.cache": [
      "packages/cms/ui/rollup.config.cjs",
      "@nx/rollup/plugin"
    ],
    "targets.build.dependsOn": [
      "packages/cms/ui/rollup.config.cjs",
      "@nx/rollup/plugin"
    ],
    "targets.build.inputs": [
      "packages/cms/ui/rollup.config.cjs",
      "@nx/rollup/plugin"
    ],
    "targets.build.outputs": [
      "packages/cms/ui/rollup.config.cjs",
      "@nx/rollup/plugin"
    ],
    "targets.build.metadata": [
      "packages/cms/ui/rollup.config.cjs",
      "@nx/rollup/plugin"
    ],
    "targets.build.executor": [
      "packages/cms/ui/rollup.config.cjs",
      "@nx/rollup/plugin"
    ],
    "targets.build.options.cwd": [
      "packages/cms/ui/rollup.config.cjs",
      "@nx/rollup/plugin"
    ],
    "targets.build.options.command": [
      "packages/cms/ui/rollup.config.cjs",
      "@nx/rollup/plugin"
    ],
    "targets.build.metadata.technologies": [
      "packages/cms/ui/rollup.config.cjs",
      "@nx/rollup/plugin"
    ],
    "targets.build.metadata.technologies.0": [
      "packages/cms/ui/rollup.config.cjs",
      "@nx/rollup/plugin"
    ],
    "targets.build.metadata.description": [
      "packages/cms/ui/rollup.config.cjs",
      "@nx/rollup/plugin"
    ],
    "targets.build.metadata.help": [
      "packages/cms/ui/rollup.config.cjs",
      "@nx/rollup/plugin"
    ],
    "targets.build.metadata.help.command": [
      "packages/cms/ui/rollup.config.cjs",
      "@nx/rollup/plugin"
    ],
    "targets.build.metadata.help.example": [
      "packages/cms/ui/rollup.config.cjs",
      "@nx/rollup/plugin"
    ],
    "targets.build-deps": [
      "packages/cms/ui/rollup.config.cjs",
      "@nx/rollup/plugin"
    ],
    "targets.build-deps.dependsOn": [
      "packages/cms/ui/rollup.config.cjs",
      "@nx/rollup/plugin"
    ],
    "targets.watch-deps": [
      "packages/cms/ui/rollup.config.cjs",
      "@nx/rollup/plugin"
    ],
    "targets.watch-deps.continuous": [
      "packages/cms/ui/rollup.config.cjs",
      "@nx/rollup/plugin"
    ],
    "targets.watch-deps.dependsOn": [
      "packages/cms/ui/rollup.config.cjs",
      "@nx/rollup/plugin"
    ],
    "targets.watch-deps.executor": [
      "packages/cms/ui/rollup.config.cjs",
      "@nx/rollup/plugin"
    ],
    "targets.watch-deps.options": [
      "packages/cms/ui/rollup.config.cjs",
      "@nx/rollup/plugin"
    ],
    "targets.watch-deps.options.command": [
      "packages/cms/ui/rollup.config.cjs",
      "@nx/rollup/plugin"
    ],
    "name": [
      "packages/cms/ui/package.json",
      "nx/core/package-json"
    ],
    "tags": [
      "packages/cms/ui/package.json",
      "nx/core/package-json"
    ],
    "tags.npm:public": [
      "packages/cms/ui/package.json",
      "nx/core/package-json"
    ],
    "metadata.targetGroups": [
      "packages/cms/ui/package.json",
      "nx/core/package-json"
    ],
    "metadata.js": [
      "packages/cms/ui/package.json",
      "nx/core/package-json"
    ],
    "metadata.js.packageName": [
      "packages/cms/ui/package.json",
      "nx/core/package-json"
    ],
    "metadata.js.packageVersion": [
      "packages/cms/ui/package.json",
      "nx/core/package-json"
    ],
    "metadata.js.packageExports": [
      "packages/cms/ui/package.json",
      "nx/core/package-json"
    ],
    "metadata.js.packageMain": [
      "packages/cms/ui/package.json",
      "nx/core/package-json"
    ],
    "metadata.js.isInPackageManagerWorkspaces": [
      "packages/cms/ui/package.json",
      "nx/core/package-json"
    ],
    "targets.nx-release-publish": [
      "packages/cms/ui/package.json",
      "nx/core/package-json"
    ],
    "targets.nx-release-publish.executor": [
      "packages/cms/ui/package.json",
      "nx/core/package-json"
    ],
    "targets.nx-release-publish.dependsOn": [
      "packages/cms/ui/package.json",
      "nx/core/package-json"
    ],
    "targets.nx-release-publish.options": [
      "packages/cms/ui/package.json",
      "nx/core/package-json"
    ],
    "targets.test.dependsOn": [
      "nx.json",
      "nx/target-defaults"
    ],
    "targets.test.parallelism": [
      "nx.json",
      "nx/target-defaults"
    ]
  },
  "packages/protocol-33": {
    "root": [
      "packages/protocol-33/project.json",
      "nx/core/project-json"
    ],
    "targets": [
      "packages/protocol-33/tsconfig.json",
      "@nx/js/typescript"
    ],
    "targets.typecheck": [
      "packages/protocol-33/tsconfig.json",
      "@nx/js/typescript"
    ],
    "targets.typecheck.dependsOn": [
      "packages/protocol-33/tsconfig.json",
      "@nx/js/typescript"
    ],
    "targets.typecheck.options": [
      "packages/protocol-33/tsconfig.json",
      "@nx/js/typescript"
    ],
    "targets.typecheck.cache": [
      "packages/protocol-33/tsconfig.json",
      "@nx/js/typescript"
    ],
    "targets.typecheck.inputs": [
      "packages/protocol-33/tsconfig.json",
      "@nx/js/typescript"
    ],
    "targets.typecheck.outputs": [
      "packages/protocol-33/tsconfig.json",
      "@nx/js/typescript"
    ],
    "targets.typecheck.syncGenerators": [
      "packages/protocol-33/tsconfig.json",
      "@nx/js/typescript"
    ],
    "targets.typecheck.metadata": [
      "packages/protocol-33/tsconfig.json",
      "@nx/js/typescript"
    ],
    "targets.typecheck.executor": [
      "packages/protocol-33/tsconfig.json",
      "@nx/js/typescript"
    ],
    "targets.typecheck.options.cwd": [
      "packages/protocol-33/tsconfig.json",
      "@nx/js/typescript"
    ],
    "targets.typecheck.options.command": [
      "packages/protocol-33/tsconfig.json",
      "@nx/js/typescript"
    ],
    "targets.typecheck.metadata.technologies": [
      "packages/protocol-33/tsconfig.json",
      "@nx/js/typescript"
    ],
    "targets.typecheck.metadata.technologies.0": [
      "packages/protocol-33/tsconfig.json",
      "@nx/js/typescript"
    ],
    "targets.typecheck.metadata.description": [
      "packages/protocol-33/tsconfig.json",
      "@nx/js/typescript"
    ],
    "targets.typecheck.metadata.help": [
      "packages/protocol-33/tsconfig.json",
      "@nx/js/typescript"
    ],
    "targets.typecheck.metadata.help.command": [
      "packages/protocol-33/tsconfig.json",
      "@nx/js/typescript"
    ],
    "targets.typecheck.metadata.help.example": [
      "packages/protocol-33/tsconfig.json",
      "@nx/js/typescript"
    ],
    "name": [
      "packages/protocol-33/project.json",
      "nx/core/project-json"
    ],
    "tags": [
      "packages/protocol-33/package.json",
      "nx/core/package-json"
    ],
    "tags.npm:public": [
      "packages/protocol-33/package.json",
      "nx/core/package-json"
    ],
    "metadata.targetGroups": [
      "packages/protocol-33/package.json",
      "nx/core/package-json"
    ],
    "metadata.js": [
      "packages/protocol-33/package.json",
      "nx/core/package-json"
    ],
    "metadata.js.packageName": [
      "packages/protocol-33/package.json",
      "nx/core/package-json"
    ],
    "metadata.js.packageVersion": [
      "packages/protocol-33/package.json",
      "nx/core/package-json"
    ],
    "metadata.js.packageExports": [
      "packages/protocol-33/package.json",
      "nx/core/package-json"
    ],
    "metadata.js.packageMain": [
      "packages/protocol-33/package.json",
      "nx/core/package-json"
    ],
    "metadata.js.isInPackageManagerWorkspaces": [
      "packages/protocol-33/package.json",
      "nx/core/package-json"
    ],
    "targets.nx-release-publish": [
      "packages/protocol-33/package.json",
      "nx/core/package-json"
    ],
    "targets.nx-release-publish.executor": [
      "packages/protocol-33/package.json",
      "nx/core/package-json"
    ],
    "targets.nx-release-publish.dependsOn": [
      "packages/protocol-33/package.json",
      "nx/core/package-json"
    ],
    "targets.nx-release-publish.options": [
      "packages/protocol-33/package.json",
      "nx/core/package-json"
    ],
    "$schema": [
      "packages/protocol-33/project.json",
      "nx/core/project-json"
    ],
    "sourceRoot": [
      "packages/protocol-33/project.json",
      "nx/core/project-json"
    ],
    "projectType": [
      "packages/protocol-33/project.json",
      "nx/core/project-json"
    ],
    "tags.scope:shared": [
      "packages/protocol-33/project.json",
      "nx/core/project-json"
    ],
    "tags.type:util": [
      "packages/protocol-33/project.json",
      "nx/core/project-json"
    ],
    "targets.build": [
      "packages/protocol-33/project.json",
      "nx/core/project-json"
    ],
    "targets.build.executor": [
      "packages/protocol-33/project.json",
      "nx/core/project-json"
    ],
    "targets.build.outputs": [
      "packages/protocol-33/project.json",
      "nx/core/project-json"
    ],
    "targets.build.options": [
      "packages/protocol-33/project.json",
      "nx/core/project-json"
    ],
    "targets.build.options.outputPath": [
      "packages/protocol-33/project.json",
      "nx/core/project-json"
    ],
    "targets.build.options.main": [
      "packages/protocol-33/project.json",
      "nx/core/project-json"
    ],
    "targets.build.options.tsConfig": [
      "packages/protocol-33/project.json",
      "nx/core/project-json"
    ],
    "targets.build.options.assets": [
      "packages/protocol-33/project.json",
      "nx/core/project-json"
    ],
    "targets.lint": [
      "packages/protocol-33/project.json",
      "nx/core/project-json"
    ],
    "targets.lint.executor": [
      "packages/protocol-33/project.json",
      "nx/core/project-json"
    ],
    "targets.test": [
      "packages/protocol-33/project.json",
      "nx/core/project-json"
    ],
    "targets.test.executor": [
      "packages/protocol-33/project.json",
      "nx/core/project-json"
    ],
    "targets.test.outputs": [
      "packages/protocol-33/project.json",
      "nx/core/project-json"
    ],
    "targets.test.options": [
      "packages/protocol-33/project.json",
      "nx/core/project-json"
    ],
    "targets.test.options.jestConfig": [
      "packages/protocol-33/project.json",
      "nx/core/project-json"
    ],
    "targets.test.dependsOn": [
      "nx.json",
      "nx/target-defaults"
    ],
    "targets.test.parallelism": [
      "nx.json",
      "nx/target-defaults"
    ]
  },
  "apps/cms-admin": {
    "root": [
      "apps/cms-admin/project.json",
      "nx/core/project-json"
    ],
    "targets": [
      "apps/cms-admin/next.config.js",
      "@nx/next/plugin"
    ],
    "targets.dev": [
      "apps/cms-admin/next.config.js",
      "@nx/next/plugin"
    ],
    "targets.dev.continuous": [
      "apps/cms-admin/next.config.js",
      "@nx/next/plugin"
    ],
    "targets.dev.options": [
      "apps/cms-admin/next.config.js",
      "@nx/next/plugin"
    ],
    "targets.dev.executor": [
      "apps/cms-admin/next.config.js",
      "@nx/next/plugin"
    ],
    "targets.dev.options.cwd": [
      "apps/cms-admin/next.config.js",
      "@nx/next/plugin"
    ],
    "targets.dev.options.command": [
      "apps/cms-admin/next.config.js",
      "@nx/next/plugin"
    ],
    "targets.start": [
      "apps/cms-admin/next.config.js",
      "@nx/next/plugin"
    ],
    "targets.start.continuous": [
      "apps/cms-admin/next.config.js",
      "@nx/next/plugin"
    ],
    "targets.start.options": [
      "apps/cms-admin/next.config.js",
      "@nx/next/plugin"
    ],
    "targets.start.dependsOn": [
      "apps/cms-admin/next.config.js",
      "@nx/next/plugin"
    ],
    "targets.start.executor": [
      "apps/cms-admin/next.config.js",
      "@nx/next/plugin"
    ],
    "targets.start.options.cwd": [
      "apps/cms-admin/next.config.js",
      "@nx/next/plugin"
    ],
    "targets.start.options.command": [
      "apps/cms-admin/next.config.js",
      "@nx/next/plugin"
    ],
    "targets.serve-static": [
      "apps/cms-admin/next.config.js",
      "@nx/next/plugin"
    ],
    "targets.serve-static.continuous": [
      "apps/cms-admin/next.config.js",
      "@nx/next/plugin"
    ],
    "targets.serve-static.options": [
      "apps/cms-admin/next.config.js",
      "@nx/next/plugin"
    ],
    "targets.serve-static.dependsOn": [
      "apps/cms-admin/next.config.js",
      "@nx/next/plugin"
    ],
    "targets.serve-static.executor": [
      "apps/cms-admin/next.config.js",
      "@nx/next/plugin"
    ],
    "targets.serve-static.options.cwd": [
      "apps/cms-admin/next.config.js",
      "@nx/next/plugin"
    ],
    "targets.serve-static.options.command": [
      "apps/cms-admin/next.config.js",
      "@nx/next/plugin"
    ],
    "targets.watch-deps": [
      "apps/cms-admin/next.config.js",
      "@nx/next/plugin"
    ],
    "targets.watch-deps.continuous": [
      "apps/cms-admin/next.config.js",
      "@nx/next/plugin"
    ],
    "targets.watch-deps.dependsOn": [
      "apps/cms-admin/next.config.js",
      "@nx/next/plugin"
    ],
    "targets.watch-deps.executor": [
      "apps/cms-admin/next.config.js",
      "@nx/next/plugin"
    ],
    "targets.watch-deps.options": [
      "apps/cms-admin/next.config.js",
      "@nx/next/plugin"
    ],
    "targets.watch-deps.options.command": [
      "apps/cms-admin/next.config.js",
      "@nx/next/plugin"
    ],
    "targets.test": [
      "apps/cms-admin/jest.config.ts",
      "@nx/jest/plugin"
    ],
    "targets.test.options": [
      "apps/cms-admin/jest.config.ts",
      "@nx/jest/plugin"
    ],
    "targets.test.metadata": [
      "apps/cms-admin/jest.config.ts",
      "@nx/jest/plugin"
    ],
    "targets.test.cache": [
      "apps/cms-admin/jest.config.ts",
      "@nx/jest/plugin"
    ],
    "targets.test.inputs": [
      "apps/cms-admin/jest.config.ts",
      "@nx/jest/plugin"
    ],
    "targets.test.outputs": [
      "apps/cms-admin/jest.config.ts",
      "@nx/jest/plugin"
    ],
    "targets.test.executor": [
      "apps/cms-admin/jest.config.ts",
      "@nx/jest/plugin"
    ],
    "targets.test.options.cwd": [
      "apps/cms-admin/jest.config.ts",
      "@nx/jest/plugin"
    ],
    "targets.test.options.env": [
      "apps/cms-admin/jest.config.ts",
      "@nx/jest/plugin"
    ],
    "targets.test.options.command": [
      "apps/cms-admin/jest.config.ts",
      "@nx/jest/plugin"
    ],
    "targets.test.metadata.technologies": [
      "apps/cms-admin/jest.config.ts",
      "@nx/jest/plugin"
    ],
    "targets.test.metadata.technologies.0": [
      "apps/cms-admin/jest.config.ts",
      "@nx/jest/plugin"
    ],
    "targets.test.metadata.description": [
      "apps/cms-admin/jest.config.ts",
      "@nx/jest/plugin"
    ],
    "targets.test.metadata.help": [
      "apps/cms-admin/jest.config.ts",
      "@nx/jest/plugin"
    ],
    "targets.test.metadata.help.command": [
      "apps/cms-admin/jest.config.ts",
      "@nx/jest/plugin"
    ],
    "targets.test.metadata.help.example": [
      "apps/cms-admin/jest.config.ts",
      "@nx/jest/plugin"
    ],
    "name": [
      "apps/cms-admin/project.json",
      "nx/core/project-json"
    ],
    "$schema": [
      "apps/cms-admin/project.json",
      "nx/core/project-json"
    ],
    "sourceRoot": [
      "apps/cms-admin/project.json",
      "nx/core/project-json"
    ],
    "projectType": [
      "apps/cms-admin/project.json",
      "nx/core/project-json"
    ],
    "tags": [
      "apps/cms-admin/project.json",
      "nx/core/project-json"
    ],
    "tags.scope:app": [
      "apps/cms-admin/project.json",
      "nx/core/project-json"
    ],
    "tags.type:ui": [
      "apps/cms-admin/project.json",
      "nx/core/project-json"
    ],
    "tags.scope:admin": [
      "apps/cms-admin/project.json",
      "nx/core/project-json"
    ],
    "targets.build": [
      "apps/cms-admin/project.json",
      "nx/core/project-json"
    ],
    "targets.build.executor": [
      "apps/cms-admin/project.json",
      "nx/core/project-json"
    ],
    "targets.build.outputs": [
      "apps/cms-admin/project.json",
      "nx/core/project-json"
    ],
    "targets.build.defaultConfiguration": [
      "apps/cms-admin/project.json",
      "nx/core/project-json"
    ],
    "targets.build.options": [
      "apps/cms-admin/project.json",
      "nx/core/project-json"
    ],
    "targets.build.options.outputPath": [
      "apps/cms-admin/project.json",
      "nx/core/project-json"
    ],
    "targets.serve": [
      "apps/cms-admin/project.json",
      "nx/core/project-json"
    ],
    "targets.serve.executor": [
      "apps/cms-admin/project.json",
      "nx/core/project-json"
    ],
    "targets.serve.defaultConfiguration": [
      "apps/cms-admin/project.json",
      "nx/core/project-json"
    ],
    "targets.serve.options": [
      "apps/cms-admin/project.json",
      "nx/core/project-json"
    ],
    "targets.serve.options.buildTarget": [
      "apps/cms-admin/project.json",
      "nx/core/project-json"
    ],
    "targets.serve.options.dev": [
      "apps/cms-admin/project.json",
      "nx/core/project-json"
    ],
    "targets.serve.options.port": [
      "apps/cms-admin/project.json",
      "nx/core/project-json"
    ],
    "targets.lint": [
      "apps/cms-admin/project.json",
      "nx/core/project-json"
    ],
    "targets.lint.executor": [
      "apps/cms-admin/project.json",
      "nx/core/project-json"
    ],
    "targets.test.dependsOn": [
      "nx.json",
      "nx/target-defaults"
    ],
    "targets.test.parallelism": [
      "nx.json",
      "nx/target-defaults"
    ]
  },
  "apps/portfolio-web": {
    "root": [
      "apps/portfolio-web/project.json",
      "nx/core/project-json"
    ],
    "targets": [
      "apps/portfolio-web/next.config.js",
      "@nx/next/plugin"
    ],
    "targets.dev": [
      "apps/portfolio-web/next.config.js",
      "@nx/next/plugin"
    ],
    "targets.dev.continuous": [
      "apps/portfolio-web/next.config.js",
      "@nx/next/plugin"
    ],
    "targets.dev.options": [
      "apps/portfolio-web/next.config.js",
      "@nx/next/plugin"
    ],
    "targets.dev.executor": [
      "apps/portfolio-web/next.config.js",
      "@nx/next/plugin"
    ],
    "targets.dev.options.cwd": [
      "apps/portfolio-web/next.config.js",
      "@nx/next/plugin"
    ],
    "targets.dev.options.command": [
      "apps/portfolio-web/next.config.js",
      "@nx/next/plugin"
    ],
    "targets.start": [
      "apps/portfolio-web/next.config.js",
      "@nx/next/plugin"
    ],
    "targets.start.continuous": [
      "apps/portfolio-web/next.config.js",
      "@nx/next/plugin"
    ],
    "targets.start.options": [
      "apps/portfolio-web/next.config.js",
      "@nx/next/plugin"
    ],
    "targets.start.dependsOn": [
      "apps/portfolio-web/next.config.js",
      "@nx/next/plugin"
    ],
    "targets.start.executor": [
      "apps/portfolio-web/next.config.js",
      "@nx/next/plugin"
    ],
    "targets.start.options.cwd": [
      "apps/portfolio-web/next.config.js",
      "@nx/next/plugin"
    ],
    "targets.start.options.command": [
      "apps/portfolio-web/next.config.js",
      "@nx/next/plugin"
    ],
    "targets.serve-static": [
      "apps/portfolio-web/next.config.js",
      "@nx/next/plugin"
    ],
    "targets.serve-static.continuous": [
      "apps/portfolio-web/next.config.js",
      "@nx/next/plugin"
    ],
    "targets.serve-static.options": [
      "apps/portfolio-web/next.config.js",
      "@nx/next/plugin"
    ],
    "targets.serve-static.dependsOn": [
      "apps/portfolio-web/next.config.js",
      "@nx/next/plugin"
    ],
    "targets.serve-static.executor": [
      "apps/portfolio-web/next.config.js",
      "@nx/next/plugin"
    ],
    "targets.serve-static.options.cwd": [
      "apps/portfolio-web/next.config.js",
      "@nx/next/plugin"
    ],
    "targets.serve-static.options.command": [
      "apps/portfolio-web/next.config.js",
      "@nx/next/plugin"
    ],
    "targets.watch-deps": [
      "apps/portfolio-web/next.config.js",
      "@nx/next/plugin"
    ],
    "targets.watch-deps.continuous": [
      "apps/portfolio-web/next.config.js",
      "@nx/next/plugin"
    ],
    "targets.watch-deps.dependsOn": [
      "apps/portfolio-web/next.config.js",
      "@nx/next/plugin"
    ],
    "targets.watch-deps.executor": [
      "apps/portfolio-web/next.config.js",
      "@nx/next/plugin"
    ],
    "targets.watch-deps.options": [
      "apps/portfolio-web/next.config.js",
      "@nx/next/plugin"
    ],
    "targets.watch-deps.options.command": [
      "apps/portfolio-web/next.config.js",
      "@nx/next/plugin"
    ],
    "name": [
      "apps/portfolio-web/project.json",
      "nx/core/project-json"
    ],
    "$schema": [
      "apps/portfolio-web/project.json",
      "nx/core/project-json"
    ],
    "sourceRoot": [
      "apps/portfolio-web/project.json",
      "nx/core/project-json"
    ],
    "projectType": [
      "apps/portfolio-web/project.json",
      "nx/core/project-json"
    ],
    "tags": [
      "apps/portfolio-web/project.json",
      "nx/core/project-json"
    ],
    "tags.scope:app": [
      "apps/portfolio-web/project.json",
      "nx/core/project-json"
    ],
    "tags.type:ui": [
      "apps/portfolio-web/project.json",
      "nx/core/project-json"
    ],
    "targets.build": [
      "apps/portfolio-web/project.json",
      "nx/core/project-json"
    ],
    "targets.build.executor": [
      "apps/portfolio-web/project.json",
      "nx/core/project-json"
    ],
    "targets.build.outputs": [
      "apps/portfolio-web/project.json",
      "nx/core/project-json"
    ],
    "targets.build.defaultConfiguration": [
      "apps/portfolio-web/project.json",
      "nx/core/project-json"
    ],
    "targets.build.options": [
      "apps/portfolio-web/project.json",
      "nx/core/project-json"
    ],
    "targets.build.configurations": [
      "apps/portfolio-web/project.json",
      "nx/core/project-json"
    ],
    "targets.build.options.outputPath": [
      "apps/portfolio-web/project.json",
      "nx/core/project-json"
    ],
    "targets.build.configurations.development": [
      "apps/portfolio-web/project.json",
      "nx/core/project-json"
    ],
    "targets.build.configurations.development.outputPath": [
      "apps/portfolio-web/project.json",
      "nx/core/project-json"
    ],
    "targets.build.configurations.production": [
      "apps/portfolio-web/project.json",
      "nx/core/project-json"
    ],
    "targets.serve": [
      "apps/portfolio-web/project.json",
      "nx/core/project-json"
    ],
    "targets.serve.executor": [
      "apps/portfolio-web/project.json",
      "nx/core/project-json"
    ],
    "targets.serve.defaultConfiguration": [
      "apps/portfolio-web/project.json",
      "nx/core/project-json"
    ],
    "targets.serve.options": [
      "apps/portfolio-web/project.json",
      "nx/core/project-json"
    ],
    "targets.serve.configurations": [
      "apps/portfolio-web/project.json",
      "nx/core/project-json"
    ],
    "targets.serve.options.buildTarget": [
      "apps/portfolio-web/project.json",
      "nx/core/project-json"
    ],
    "targets.serve.options.dev": [
      "apps/portfolio-web/project.json",
      "nx/core/project-json"
    ],
    "targets.serve.options.port": [
      "apps/portfolio-web/project.json",
      "nx/core/project-json"
    ],
    "targets.serve.configurations.development": [
      "apps/portfolio-web/project.json",
      "nx/core/project-json"
    ],
    "targets.serve.configurations.development.buildTarget": [
      "apps/portfolio-web/project.json",
      "nx/core/project-json"
    ],
    "targets.serve.configurations.development.dev": [
      "apps/portfolio-web/project.json",
      "nx/core/project-json"
    ],
    "targets.serve.configurations.production": [
      "apps/portfolio-web/project.json",
      "nx/core/project-json"
    ],
    "targets.serve.configurations.production.buildTarget": [
      "apps/portfolio-web/project.json",
      "nx/core/project-json"
    ],
    "targets.serve.configurations.production.dev": [
      "apps/portfolio-web/project.json",
      "nx/core/project-json"
    ],
    "targets.lint": [
      "apps/portfolio-web/project.json",
      "nx/core/project-json"
    ],
    "targets.lint.executor": [
      "apps/portfolio-web/project.json",
      "nx/core/project-json"
    ],
    "targets.test": [
      "apps/portfolio-web/project.json",
      "nx/core/project-json"
    ],
    "targets.test.executor": [
      "apps/portfolio-web/project.json",
      "nx/core/project-json"
    ],
    "targets.test.outputs": [
      "apps/portfolio-web/project.json",
      "nx/core/project-json"
    ],
    "targets.test.options": [
      "apps/portfolio-web/project.json",
      "nx/core/project-json"
    ],
    "targets.test.options.jestConfig": [
      "apps/portfolio-web/project.json",
      "nx/core/project-json"
    ],
    "targets.test.options.passWithNoTests": [
      "apps/portfolio-web/project.json",
      "nx/core/project-json"
    ],
    "targets.test.dependsOn": [
      "nx.json",
      "nx/target-defaults"
    ],
    "targets.test.parallelism": [
      "nx.json",
      "nx/target-defaults"
    ]
  },
  "packages/auth-shield": {
    "root": [
      "packages/auth-shield/package.json",
      "nx/core/package-json"
    ],
    "targets": [
      "packages/auth-shield/eslint.config.mjs",
      "@nx/eslint/plugin"
    ],
    "targets.lint": [
      "packages/auth-shield/eslint.config.mjs",
      "@nx/eslint/plugin"
    ],
    "targets.lint.cache": [
      "packages/auth-shield/eslint.config.mjs",
      "@nx/eslint/plugin"
    ],
    "targets.lint.options": [
      "packages/auth-shield/eslint.config.mjs",
      "@nx/eslint/plugin"
    ],
    "targets.lint.inputs": [
      "packages/auth-shield/eslint.config.mjs",
      "@nx/eslint/plugin"
    ],
    "targets.lint.outputs": [
      "packages/auth-shield/eslint.config.mjs",
      "@nx/eslint/plugin"
    ],
    "targets.lint.metadata": [
      "packages/auth-shield/eslint.config.mjs",
      "@nx/eslint/plugin"
    ],
    "targets.lint.executor": [
      "packages/auth-shield/eslint.config.mjs",
      "@nx/eslint/plugin"
    ],
    "targets.lint.options.cwd": [
      "packages/auth-shield/eslint.config.mjs",
      "@nx/eslint/plugin"
    ],
    "targets.lint.options.command": [
      "packages/auth-shield/eslint.config.mjs",
      "@nx/eslint/plugin"
    ],
    "targets.lint.metadata.technologies": [
      "packages/auth-shield/eslint.config.mjs",
      "@nx/eslint/plugin"
    ],
    "targets.lint.metadata.technologies.0": [
      "packages/auth-shield/eslint.config.mjs",
      "@nx/eslint/plugin"
    ],
    "targets.lint.metadata.description": [
      "packages/auth-shield/eslint.config.mjs",
      "@nx/eslint/plugin"
    ],
    "targets.lint.metadata.help": [
      "packages/auth-shield/eslint.config.mjs",
      "@nx/eslint/plugin"
    ],
    "targets.lint.metadata.help.command": [
      "packages/auth-shield/eslint.config.mjs",
      "@nx/eslint/plugin"
    ],
    "targets.lint.metadata.help.example": [
      "packages/auth-shield/eslint.config.mjs",
      "@nx/eslint/plugin"
    ],
    "targets.test": [
      "packages/auth-shield/jest.config.ts",
      "@nx/jest/plugin"
    ],
    "targets.test.options": [
      "packages/auth-shield/jest.config.ts",
      "@nx/jest/plugin"
    ],
    "targets.test.metadata": [
      "packages/auth-shield/jest.config.ts",
      "@nx/jest/plugin"
    ],
    "targets.test.cache": [
      "packages/auth-shield/jest.config.ts",
      "@nx/jest/plugin"
    ],
    "targets.test.inputs": [
      "packages/auth-shield/jest.config.ts",
      "@nx/jest/plugin"
    ],
    "targets.test.outputs": [
      "packages/auth-shield/jest.config.ts",
      "@nx/jest/plugin"
    ],
    "targets.test.executor": [
      "packages/auth-shield/jest.config.ts",
      "@nx/jest/plugin"
    ],
    "targets.test.options.cwd": [
      "packages/auth-shield/jest.config.ts",
      "@nx/jest/plugin"
    ],
    "targets.test.options.env": [
      "packages/auth-shield/jest.config.ts",
      "@nx/jest/plugin"
    ],
    "targets.test.options.command": [
      "packages/auth-shield/jest.config.ts",
      "@nx/jest/plugin"
    ],
    "targets.test.metadata.technologies": [
      "packages/auth-shield/jest.config.ts",
      "@nx/jest/plugin"
    ],
    "targets.test.metadata.technologies.0": [
      "packages/auth-shield/jest.config.ts",
      "@nx/jest/plugin"
    ],
    "targets.test.metadata.description": [
      "packages/auth-shield/jest.config.ts",
      "@nx/jest/plugin"
    ],
    "targets.test.metadata.help": [
      "packages/auth-shield/jest.config.ts",
      "@nx/jest/plugin"
    ],
    "targets.test.metadata.help.command": [
      "packages/auth-shield/jest.config.ts",
      "@nx/jest/plugin"
    ],
    "targets.test.metadata.help.example": [
      "packages/auth-shield/jest.config.ts",
      "@nx/jest/plugin"
    ],
    "targets.typecheck": [
      "packages/auth-shield/tsconfig.json",
      "@nx/js/typescript"
    ],
    "targets.typecheck.dependsOn": [
      "packages/auth-shield/tsconfig.json",
      "@nx/js/typescript"
    ],
    "targets.typecheck.options": [
      "packages/auth-shield/tsconfig.json",
      "@nx/js/typescript"
    ],
    "targets.typecheck.cache": [
      "packages/auth-shield/tsconfig.json",
      "@nx/js/typescript"
    ],
    "targets.typecheck.inputs": [
      "packages/auth-shield/tsconfig.json",
      "@nx/js/typescript"
    ],
    "targets.typecheck.outputs": [
      "packages/auth-shield/tsconfig.json",
      "@nx/js/typescript"
    ],
    "targets.typecheck.syncGenerators": [
      "packages/auth-shield/tsconfig.json",
      "@nx/js/typescript"
    ],
    "targets.typecheck.metadata": [
      "packages/auth-shield/tsconfig.json",
      "@nx/js/typescript"
    ],
    "targets.typecheck.executor": [
      "packages/auth-shield/tsconfig.json",
      "@nx/js/typescript"
    ],
    "targets.typecheck.options.cwd": [
      "packages/auth-shield/tsconfig.json",
      "@nx/js/typescript"
    ],
    "targets.typecheck.options.command": [
      "packages/auth-shield/tsconfig.json",
      "@nx/js/typescript"
    ],
    "targets.typecheck.metadata.technologies": [
      "packages/auth-shield/tsconfig.json",
      "@nx/js/typescript"
    ],
    "targets.typecheck.metadata.technologies.0": [
      "packages/auth-shield/tsconfig.json",
      "@nx/js/typescript"
    ],
    "targets.typecheck.metadata.description": [
      "packages/auth-shield/tsconfig.json",
      "@nx/js/typescript"
    ],
    "targets.typecheck.metadata.help": [
      "packages/auth-shield/tsconfig.json",
      "@nx/js/typescript"
    ],
    "targets.typecheck.metadata.help.command": [
      "packages/auth-shield/tsconfig.json",
      "@nx/js/typescript"
    ],
    "targets.typecheck.metadata.help.example": [
      "packages/auth-shield/tsconfig.json",
      "@nx/js/typescript"
    ],
    "targets.build": [
      "packages/auth-shield/tsconfig.lib.json",
      "@nx/js/typescript"
    ],
    "targets.build.dependsOn": [
      "packages/auth-shield/tsconfig.lib.json",
      "@nx/js/typescript"
    ],
    "targets.build.options": [
      "packages/auth-shield/tsconfig.lib.json",
      "@nx/js/typescript"
    ],
    "targets.build.cache": [
      "packages/auth-shield/tsconfig.lib.json",
      "@nx/js/typescript"
    ],
    "targets.build.inputs": [
      "packages/auth-shield/tsconfig.lib.json",
      "@nx/js/typescript"
    ],
    "targets.build.outputs": [
      "packages/auth-shield/tsconfig.lib.json",
      "@nx/js/typescript"
    ],
    "targets.build.syncGenerators": [
      "packages/auth-shield/tsconfig.lib.json",
      "@nx/js/typescript"
    ],
    "targets.build.metadata": [
      "packages/auth-shield/tsconfig.lib.json",
      "@nx/js/typescript"
    ],
    "targets.build.executor": [
      "packages/auth-shield/tsconfig.lib.json",
      "@nx/js/typescript"
    ],
    "targets.build.options.cwd": [
      "packages/auth-shield/tsconfig.lib.json",
      "@nx/js/typescript"
    ],
    "targets.build.options.command": [
      "packages/auth-shield/tsconfig.lib.json",
      "@nx/js/typescript"
    ],
    "targets.build.metadata.technologies": [
      "packages/auth-shield/tsconfig.lib.json",
      "@nx/js/typescript"
    ],
    "targets.build.metadata.technologies.0": [
      "packages/auth-shield/tsconfig.lib.json",
      "@nx/js/typescript"
    ],
    "targets.build.metadata.description": [
      "packages/auth-shield/tsconfig.lib.json",
      "@nx/js/typescript"
    ],
    "targets.build.metadata.help": [
      "packages/auth-shield/tsconfig.lib.json",
      "@nx/js/typescript"
    ],
    "targets.build.metadata.help.command": [
      "packages/auth-shield/tsconfig.lib.json",
      "@nx/js/typescript"
    ],
    "targets.build.metadata.help.example": [
      "packages/auth-shield/tsconfig.lib.json",
      "@nx/js/typescript"
    ],
    "targets.build-deps": [
      "packages/auth-shield/tsconfig.lib.json",
      "@nx/js/typescript"
    ],
    "targets.build-deps.dependsOn": [
      "packages/auth-shield/tsconfig.lib.json",
      "@nx/js/typescript"
    ],
    "targets.watch-deps": [
      "packages/auth-shield/tsconfig.lib.json",
      "@nx/js/typescript"
    ],
    "targets.watch-deps.continuous": [
      "packages/auth-shield/tsconfig.lib.json",
      "@nx/js/typescript"
    ],
    "targets.watch-deps.dependsOn": [
      "packages/auth-shield/tsconfig.lib.json",
      "@nx/js/typescript"
    ],
    "targets.watch-deps.executor": [
      "packages/auth-shield/tsconfig.lib.json",
      "@nx/js/typescript"
    ],
    "targets.watch-deps.options": [
      "packages/auth-shield/tsconfig.lib.json",
      "@nx/js/typescript"
    ],
    "targets.watch-deps.options.command": [
      "packages/auth-shield/tsconfig.lib.json",
      "@nx/js/typescript"
    ],
    "name": [
      "packages/auth-shield/package.json",
      "nx/core/package-json"
    ],
    "tags": [
      "packages/auth-shield/package.json",
      "nx/core/package-json"
    ],
    "tags.npm:public": [
      "packages/auth-shield/package.json",
      "nx/core/package-json"
    ],
    "metadata.targetGroups": [
      "packages/auth-shield/package.json",
      "nx/core/package-json"
    ],
    "metadata.js": [
      "packages/auth-shield/package.json",
      "nx/core/package-json"
    ],
    "metadata.js.packageName": [
      "packages/auth-shield/package.json",
      "nx/core/package-json"
    ],
    "metadata.js.packageVersion": [
      "packages/auth-shield/package.json",
      "nx/core/package-json"
    ],
    "metadata.js.packageExports": [
      "packages/auth-shield/package.json",
      "nx/core/package-json"
    ],
    "metadata.js.packageMain": [
      "packages/auth-shield/package.json",
      "nx/core/package-json"
    ],
    "metadata.js.isInPackageManagerWorkspaces": [
      "packages/auth-shield/package.json",
      "nx/core/package-json"
    ],
    "targets.nx-release-publish": [
      "packages/auth-shield/package.json",
      "nx/core/package-json"
    ],
    "targets.nx-release-publish.executor": [
      "packages/auth-shield/package.json",
      "nx/core/package-json"
    ],
    "targets.nx-release-publish.dependsOn": [
      "packages/auth-shield/package.json",
      "nx/core/package-json"
    ],
    "targets.nx-release-publish.options": [
      "packages/auth-shield/package.json",
      "nx/core/package-json"
    ],
    "targets.test.dependsOn": [
      "nx.json",
      "nx/target-defaults"
    ],
    "targets.test.parallelism": [
      "nx.json",
      "nx/target-defaults"
    ]
  },
  "packages/cms/core": {
    "root": [
      "packages/cms/core/package.json",
      "nx/core/package-json"
    ],
    "targets": [
      "packages/cms/core/eslint.config.mjs",
      "@nx/eslint/plugin"
    ],
    "targets.lint": [
      "packages/cms/core/eslint.config.mjs",
      "@nx/eslint/plugin"
    ],
    "targets.lint.cache": [
      "packages/cms/core/eslint.config.mjs",
      "@nx/eslint/plugin"
    ],
    "targets.lint.options": [
      "packages/cms/core/eslint.config.mjs",
      "@nx/eslint/plugin"
    ],
    "targets.lint.inputs": [
      "packages/cms/core/eslint.config.mjs",
      "@nx/eslint/plugin"
    ],
    "targets.lint.outputs": [
      "packages/cms/core/eslint.config.mjs",
      "@nx/eslint/plugin"
    ],
    "targets.lint.metadata": [
      "packages/cms/core/eslint.config.mjs",
      "@nx/eslint/plugin"
    ],
    "targets.lint.executor": [
      "packages/cms/core/eslint.config.mjs",
      "@nx/eslint/plugin"
    ],
    "targets.lint.options.cwd": [
      "packages/cms/core/eslint.config.mjs",
      "@nx/eslint/plugin"
    ],
    "targets.lint.options.command": [
      "packages/cms/core/eslint.config.mjs",
      "@nx/eslint/plugin"
    ],
    "targets.lint.metadata.technologies": [
      "packages/cms/core/eslint.config.mjs",
      "@nx/eslint/plugin"
    ],
    "targets.lint.metadata.technologies.0": [
      "packages/cms/core/eslint.config.mjs",
      "@nx/eslint/plugin"
    ],
    "targets.lint.metadata.description": [
      "packages/cms/core/eslint.config.mjs",
      "@nx/eslint/plugin"
    ],
    "targets.lint.metadata.help": [
      "packages/cms/core/eslint.config.mjs",
      "@nx/eslint/plugin"
    ],
    "targets.lint.metadata.help.command": [
      "packages/cms/core/eslint.config.mjs",
      "@nx/eslint/plugin"
    ],
    "targets.lint.metadata.help.example": [
      "packages/cms/core/eslint.config.mjs",
      "@nx/eslint/plugin"
    ],
    "targets.test": [
      "packages/cms/core/jest.config.ts",
      "@nx/jest/plugin"
    ],
    "targets.test.options": [
      "packages/cms/core/jest.config.ts",
      "@nx/jest/plugin"
    ],
    "targets.test.metadata": [
      "packages/cms/core/jest.config.ts",
      "@nx/jest/plugin"
    ],
    "targets.test.cache": [
      "packages/cms/core/jest.config.ts",
      "@nx/jest/plugin"
    ],
    "targets.test.inputs": [
      "packages/cms/core/jest.config.ts",
      "@nx/jest/plugin"
    ],
    "targets.test.outputs": [
      "packages/cms/core/jest.config.ts",
      "@nx/jest/plugin"
    ],
    "targets.test.executor": [
      "packages/cms/core/jest.config.ts",
      "@nx/jest/plugin"
    ],
    "targets.test.options.cwd": [
      "packages/cms/core/jest.config.ts",
      "@nx/jest/plugin"
    ],
    "targets.test.options.env": [
      "packages/cms/core/jest.config.ts",
      "@nx/jest/plugin"
    ],
    "targets.test.options.command": [
      "packages/cms/core/jest.config.ts",
      "@nx/jest/plugin"
    ],
    "targets.test.metadata.technologies": [
      "packages/cms/core/jest.config.ts",
      "@nx/jest/plugin"
    ],
    "targets.test.metadata.technologies.0": [
      "packages/cms/core/jest.config.ts",
      "@nx/jest/plugin"
    ],
    "targets.test.metadata.description": [
      "packages/cms/core/jest.config.ts",
      "@nx/jest/plugin"
    ],
    "targets.test.metadata.help": [
      "packages/cms/core/jest.config.ts",
      "@nx/jest/plugin"
    ],
    "targets.test.metadata.help.command": [
      "packages/cms/core/jest.config.ts",
      "@nx/jest/plugin"
    ],
    "targets.test.metadata.help.example": [
      "packages/cms/core/jest.config.ts",
      "@nx/jest/plugin"
    ],
    "targets.typecheck": [
      "packages/cms/core/tsconfig.json",
      "@nx/js/typescript"
    ],
    "targets.typecheck.dependsOn": [
      "packages/cms/core/tsconfig.json",
      "@nx/js/typescript"
    ],
    "targets.typecheck.options": [
      "packages/cms/core/tsconfig.json",
      "@nx/js/typescript"
    ],
    "targets.typecheck.cache": [
      "packages/cms/core/tsconfig.json",
      "@nx/js/typescript"
    ],
    "targets.typecheck.inputs": [
      "packages/cms/core/tsconfig.json",
      "@nx/js/typescript"
    ],
    "targets.typecheck.outputs": [
      "packages/cms/core/tsconfig.json",
      "@nx/js/typescript"
    ],
    "targets.typecheck.syncGenerators": [
      "packages/cms/core/tsconfig.json",
      "@nx/js/typescript"
    ],
    "targets.typecheck.metadata": [
      "packages/cms/core/tsconfig.json",
      "@nx/js/typescript"
    ],
    "targets.typecheck.executor": [
      "packages/cms/core/tsconfig.json",
      "@nx/js/typescript"
    ],
    "targets.typecheck.options.cwd": [
      "packages/cms/core/tsconfig.json",
      "@nx/js/typescript"
    ],
    "targets.typecheck.options.command": [
      "packages/cms/core/tsconfig.json",
      "@nx/js/typescript"
    ],
    "targets.typecheck.metadata.technologies": [
      "packages/cms/core/tsconfig.json",
      "@nx/js/typescript"
    ],
    "targets.typecheck.metadata.technologies.0": [
      "packages/cms/core/tsconfig.json",
      "@nx/js/typescript"
    ],
    "targets.typecheck.metadata.description": [
      "packages/cms/core/tsconfig.json",
      "@nx/js/typescript"
    ],
    "targets.typecheck.metadata.help": [
      "packages/cms/core/tsconfig.json",
      "@nx/js/typescript"
    ],
    "targets.typecheck.metadata.help.command": [
      "packages/cms/core/tsconfig.json",
      "@nx/js/typescript"
    ],
    "targets.typecheck.metadata.help.example": [
      "packages/cms/core/tsconfig.json",
      "@nx/js/typescript"
    ],
    "targets.build": [
      "packages/cms/core/tsconfig.lib.json",
      "@nx/js/typescript"
    ],
    "targets.build.dependsOn": [
      "packages/cms/core/tsconfig.lib.json",
      "@nx/js/typescript"
    ],
    "targets.build.options": [
      "packages/cms/core/tsconfig.lib.json",
      "@nx/js/typescript"
    ],
    "targets.build.cache": [
      "packages/cms/core/tsconfig.lib.json",
      "@nx/js/typescript"
    ],
    "targets.build.inputs": [
      "packages/cms/core/tsconfig.lib.json",
      "@nx/js/typescript"
    ],
    "targets.build.outputs": [
      "packages/cms/core/tsconfig.lib.json",
      "@nx/js/typescript"
    ],
    "targets.build.syncGenerators": [
      "packages/cms/core/tsconfig.lib.json",
      "@nx/js/typescript"
    ],
    "targets.build.metadata": [
      "packages/cms/core/tsconfig.lib.json",
      "@nx/js/typescript"
    ],
    "targets.build.executor": [
      "packages/cms/core/tsconfig.lib.json",
      "@nx/js/typescript"
    ],
    "targets.build.options.cwd": [
      "packages/cms/core/tsconfig.lib.json",
      "@nx/js/typescript"
    ],
    "targets.build.options.command": [
      "packages/cms/core/tsconfig.lib.json",
      "@nx/js/typescript"
    ],
    "targets.build.metadata.technologies": [
      "packages/cms/core/tsconfig.lib.json",
      "@nx/js/typescript"
    ],
    "targets.build.metadata.technologies.0": [
      "packages/cms/core/tsconfig.lib.json",
      "@nx/js/typescript"
    ],
    "targets.build.metadata.description": [
      "packages/cms/core/tsconfig.lib.json",
      "@nx/js/typescript"
    ],
    "targets.build.metadata.help": [
      "packages/cms/core/tsconfig.lib.json",
      "@nx/js/typescript"
    ],
    "targets.build.metadata.help.command": [
      "packages/cms/core/tsconfig.lib.json",
      "@nx/js/typescript"
    ],
    "targets.build.metadata.help.example": [
      "packages/cms/core/tsconfig.lib.json",
      "@nx/js/typescript"
    ],
    "targets.build-deps": [
      "packages/cms/core/tsconfig.lib.json",
      "@nx/js/typescript"
    ],
    "targets.build-deps.dependsOn": [
      "packages/cms/core/tsconfig.lib.json",
      "@nx/js/typescript"
    ],
    "targets.watch-deps": [
      "packages/cms/core/tsconfig.lib.json",
      "@nx/js/typescript"
    ],
    "targets.watch-deps.continuous": [
      "packages/cms/core/tsconfig.lib.json",
      "@nx/js/typescript"
    ],
    "targets.watch-deps.dependsOn": [
      "packages/cms/core/tsconfig.lib.json",
      "@nx/js/typescript"
    ],
    "targets.watch-deps.executor": [
      "packages/cms/core/tsconfig.lib.json",
      "@nx/js/typescript"
    ],
    "targets.watch-deps.options": [
      "packages/cms/core/tsconfig.lib.json",
      "@nx/js/typescript"
    ],
    "targets.watch-deps.options.command": [
      "packages/cms/core/tsconfig.lib.json",
      "@nx/js/typescript"
    ],
    "name": [
      "packages/cms/core/package.json",
      "nx/core/package-json"
    ],
    "tags": [
      "packages/cms/core/package.json",
      "nx/core/package-json"
    ],
    "tags.npm:public": [
      "packages/cms/core/package.json",
      "nx/core/package-json"
    ],
    "metadata.targetGroups": [
      "packages/cms/core/package.json",
      "nx/core/package-json"
    ],
    "metadata.js": [
      "packages/cms/core/package.json",
      "nx/core/package-json"
    ],
    "metadata.js.packageName": [
      "packages/cms/core/package.json",
      "nx/core/package-json"
    ],
    "metadata.js.packageVersion": [
      "packages/cms/core/package.json",
      "nx/core/package-json"
    ],
    "metadata.js.packageExports": [
      "packages/cms/core/package.json",
      "nx/core/package-json"
    ],
    "metadata.js.packageMain": [
      "packages/cms/core/package.json",
      "nx/core/package-json"
    ],
    "metadata.js.isInPackageManagerWorkspaces": [
      "packages/cms/core/package.json",
      "nx/core/package-json"
    ],
    "targets.nx-release-publish": [
      "packages/cms/core/package.json",
      "nx/core/package-json"
    ],
    "targets.nx-release-publish.executor": [
      "packages/cms/core/package.json",
      "nx/core/package-json"
    ],
    "targets.nx-release-publish.dependsOn": [
      "packages/cms/core/package.json",
      "nx/core/package-json"
    ],
    "targets.nx-release-publish.options": [
      "packages/cms/core/package.json",
      "nx/core/package-json"
    ],
    "targets.test.dependsOn": [
      "nx.json",
      "nx/target-defaults"
    ],
    "targets.test.parallelism": [
      "nx.json",
      "nx/target-defaults"
    ]
  },
  "packages/testing-utils": {
    "root": [
      "packages/testing-utils/package.json",
      "nx/core/package-json"
    ],
    "targets": [
      "packages/testing-utils/eslint.config.mjs",
      "@nx/eslint/plugin"
    ],
    "targets.lint": [
      "packages/testing-utils/eslint.config.mjs",
      "@nx/eslint/plugin"
    ],
    "targets.lint.cache": [
      "packages/testing-utils/eslint.config.mjs",
      "@nx/eslint/plugin"
    ],
    "targets.lint.options": [
      "packages/testing-utils/eslint.config.mjs",
      "@nx/eslint/plugin"
    ],
    "targets.lint.inputs": [
      "packages/testing-utils/eslint.config.mjs",
      "@nx/eslint/plugin"
    ],
    "targets.lint.outputs": [
      "packages/testing-utils/eslint.config.mjs",
      "@nx/eslint/plugin"
    ],
    "targets.lint.metadata": [
      "packages/testing-utils/eslint.config.mjs",
      "@nx/eslint/plugin"
    ],
    "targets.lint.executor": [
      "packages/testing-utils/eslint.config.mjs",
      "@nx/eslint/plugin"
    ],
    "targets.lint.options.cwd": [
      "packages/testing-utils/eslint.config.mjs",
      "@nx/eslint/plugin"
    ],
    "targets.lint.options.command": [
      "packages/testing-utils/eslint.config.mjs",
      "@nx/eslint/plugin"
    ],
    "targets.lint.metadata.technologies": [
      "packages/testing-utils/eslint.config.mjs",
      "@nx/eslint/plugin"
    ],
    "targets.lint.metadata.technologies.0": [
      "packages/testing-utils/eslint.config.mjs",
      "@nx/eslint/plugin"
    ],
    "targets.lint.metadata.description": [
      "packages/testing-utils/eslint.config.mjs",
      "@nx/eslint/plugin"
    ],
    "targets.lint.metadata.help": [
      "packages/testing-utils/eslint.config.mjs",
      "@nx/eslint/plugin"
    ],
    "targets.lint.metadata.help.command": [
      "packages/testing-utils/eslint.config.mjs",
      "@nx/eslint/plugin"
    ],
    "targets.lint.metadata.help.example": [
      "packages/testing-utils/eslint.config.mjs",
      "@nx/eslint/plugin"
    ],
    "targets.test": [
      "packages/testing-utils/jest.config.ts",
      "@nx/jest/plugin"
    ],
    "targets.test.options": [
      "packages/testing-utils/jest.config.ts",
      "@nx/jest/plugin"
    ],
    "targets.test.metadata": [
      "packages/testing-utils/jest.config.ts",
      "@nx/jest/plugin"
    ],
    "targets.test.cache": [
      "packages/testing-utils/jest.config.ts",
      "@nx/jest/plugin"
    ],
    "targets.test.inputs": [
      "packages/testing-utils/jest.config.ts",
      "@nx/jest/plugin"
    ],
    "targets.test.outputs": [
      "packages/testing-utils/jest.config.ts",
      "@nx/jest/plugin"
    ],
    "targets.test.executor": [
      "packages/testing-utils/jest.config.ts",
      "@nx/jest/plugin"
    ],
    "targets.test.options.cwd": [
      "packages/testing-utils/jest.config.ts",
      "@nx/jest/plugin"
    ],
    "targets.test.options.env": [
      "packages/testing-utils/jest.config.ts",
      "@nx/jest/plugin"
    ],
    "targets.test.options.command": [
      "packages/testing-utils/jest.config.ts",
      "@nx/jest/plugin"
    ],
    "targets.test.metadata.technologies": [
      "packages/testing-utils/jest.config.ts",
      "@nx/jest/plugin"
    ],
    "targets.test.metadata.technologies.0": [
      "packages/testing-utils/jest.config.ts",
      "@nx/jest/plugin"
    ],
    "targets.test.metadata.description": [
      "packages/testing-utils/jest.config.ts",
      "@nx/jest/plugin"
    ],
    "targets.test.metadata.help": [
      "packages/testing-utils/jest.config.ts",
      "@nx/jest/plugin"
    ],
    "targets.test.metadata.help.command": [
      "packages/testing-utils/jest.config.ts",
      "@nx/jest/plugin"
    ],
    "targets.test.metadata.help.example": [
      "packages/testing-utils/jest.config.ts",
      "@nx/jest/plugin"
    ],
    "targets.typecheck": [
      "packages/testing-utils/tsconfig.json",
      "@nx/js/typescript"
    ],
    "targets.typecheck.dependsOn": [
      "packages/testing-utils/tsconfig.json",
      "@nx/js/typescript"
    ],
    "targets.typecheck.options": [
      "packages/testing-utils/tsconfig.json",
      "@nx/js/typescript"
    ],
    "targets.typecheck.cache": [
      "packages/testing-utils/tsconfig.json",
      "@nx/js/typescript"
    ],
    "targets.typecheck.inputs": [
      "packages/testing-utils/tsconfig.json",
      "@nx/js/typescript"
    ],
    "targets.typecheck.outputs": [
      "packages/testing-utils/tsconfig.json",
      "@nx/js/typescript"
    ],
    "targets.typecheck.syncGenerators": [
      "packages/testing-utils/tsconfig.json",
      "@nx/js/typescript"
    ],
    "targets.typecheck.metadata": [
      "packages/testing-utils/tsconfig.json",
      "@nx/js/typescript"
    ],
    "targets.typecheck.executor": [
      "packages/testing-utils/tsconfig.json",
      "@nx/js/typescript"
    ],
    "targets.typecheck.options.cwd": [
      "packages/testing-utils/tsconfig.json",
      "@nx/js/typescript"
    ],
    "targets.typecheck.options.command": [
      "packages/testing-utils/tsconfig.json",
      "@nx/js/typescript"
    ],
    "targets.typecheck.metadata.technologies": [
      "packages/testing-utils/tsconfig.json",
      "@nx/js/typescript"
    ],
    "targets.typecheck.metadata.technologies.0": [
      "packages/testing-utils/tsconfig.json",
      "@nx/js/typescript"
    ],
    "targets.typecheck.metadata.description": [
      "packages/testing-utils/tsconfig.json",
      "@nx/js/typescript"
    ],
    "targets.typecheck.metadata.help": [
      "packages/testing-utils/tsconfig.json",
      "@nx/js/typescript"
    ],
    "targets.typecheck.metadata.help.command": [
      "packages/testing-utils/tsconfig.json",
      "@nx/js/typescript"
    ],
    "targets.typecheck.metadata.help.example": [
      "packages/testing-utils/tsconfig.json",
      "@nx/js/typescript"
    ],
    "targets.build": [
      "packages/testing-utils/tsconfig.lib.json",
      "@nx/js/typescript"
    ],
    "targets.build.dependsOn": [
      "packages/testing-utils/tsconfig.lib.json",
      "@nx/js/typescript"
    ],
    "targets.build.options": [
      "packages/testing-utils/tsconfig.lib.json",
      "@nx/js/typescript"
    ],
    "targets.build.cache": [
      "packages/testing-utils/tsconfig.lib.json",
      "@nx/js/typescript"
    ],
    "targets.build.inputs": [
      "packages/testing-utils/tsconfig.lib.json",
      "@nx/js/typescript"
    ],
    "targets.build.outputs": [
      "packages/testing-utils/tsconfig.lib.json",
      "@nx/js/typescript"
    ],
    "targets.build.syncGenerators": [
      "packages/testing-utils/tsconfig.lib.json",
      "@nx/js/typescript"
    ],
    "targets.build.metadata": [
      "packages/testing-utils/tsconfig.lib.json",
      "@nx/js/typescript"
    ],
    "targets.build.executor": [
      "packages/testing-utils/tsconfig.lib.json",
      "@nx/js/typescript"
    ],
    "targets.build.options.cwd": [
      "packages/testing-utils/tsconfig.lib.json",
      "@nx/js/typescript"
    ],
    "targets.build.options.command": [
      "packages/testing-utils/tsconfig.lib.json",
      "@nx/js/typescript"
    ],
    "targets.build.metadata.technologies": [
      "packages/testing-utils/tsconfig.lib.json",
      "@nx/js/typescript"
    ],
    "targets.build.metadata.technologies.0": [
      "packages/testing-utils/tsconfig.lib.json",
      "@nx/js/typescript"
    ],
    "targets.build.metadata.description": [
      "packages/testing-utils/tsconfig.lib.json",
      "@nx/js/typescript"
    ],
    "targets.build.metadata.help": [
      "packages/testing-utils/tsconfig.lib.json",
      "@nx/js/typescript"
    ],
    "targets.build.metadata.help.command": [
      "packages/testing-utils/tsconfig.lib.json",
      "@nx/js/typescript"
    ],
    "targets.build.metadata.help.example": [
      "packages/testing-utils/tsconfig.lib.json",
      "@nx/js/typescript"
    ],
    "targets.build-deps": [
      "packages/testing-utils/tsconfig.lib.json",
      "@nx/js/typescript"
    ],
    "targets.build-deps.dependsOn": [
      "packages/testing-utils/tsconfig.lib.json",
      "@nx/js/typescript"
    ],
    "targets.watch-deps": [
      "packages/testing-utils/tsconfig.lib.json",
      "@nx/js/typescript"
    ],
    "targets.watch-deps.continuous": [
      "packages/testing-utils/tsconfig.lib.json",
      "@nx/js/typescript"
    ],
    "targets.watch-deps.dependsOn": [
      "packages/testing-utils/tsconfig.lib.json",
      "@nx/js/typescript"
    ],
    "targets.watch-deps.executor": [
      "packages/testing-utils/tsconfig.lib.json",
      "@nx/js/typescript"
    ],
    "targets.watch-deps.options": [
      "packages/testing-utils/tsconfig.lib.json",
      "@nx/js/typescript"
    ],
    "targets.watch-deps.options.command": [
      "packages/testing-utils/tsconfig.lib.json",
      "@nx/js/typescript"
    ],
    "name": [
      "packages/testing-utils/package.json",
      "nx/core/package-json"
    ],
    "tags": [
      "packages/testing-utils/package.json",
      "nx/core/package-json"
    ],
    "tags.npm:public": [
      "packages/testing-utils/package.json",
      "nx/core/package-json"
    ],
    "metadata.targetGroups": [
      "packages/testing-utils/package.json",
      "nx/core/package-json"
    ],
    "metadata.js": [
      "packages/testing-utils/package.json",
      "nx/core/package-json"
    ],
    "metadata.js.packageName": [
      "packages/testing-utils/package.json",
      "nx/core/package-json"
    ],
    "metadata.js.packageVersion": [
      "packages/testing-utils/package.json",
      "nx/core/package-json"
    ],
    "metadata.js.packageExports": [
      "packages/testing-utils/package.json",
      "nx/core/package-json"
    ],
    "metadata.js.packageMain": [
      "packages/testing-utils/package.json",
      "nx/core/package-json"
    ],
    "metadata.js.isInPackageManagerWorkspaces": [
      "packages/testing-utils/package.json",
      "nx/core/package-json"
    ],
    "targets.nx-release-publish": [
      "packages/testing-utils/package.json",
      "nx/core/package-json"
    ],
    "targets.nx-release-publish.executor": [
      "packages/testing-utils/package.json",
      "nx/core/package-json"
    ],
    "targets.nx-release-publish.dependsOn": [
      "packages/testing-utils/package.json",
      "nx/core/package-json"
    ],
    "targets.nx-release-publish.options": [
      "packages/testing-utils/package.json",
      "nx/core/package-json"
    ],
    "targets.test.dependsOn": [
      "nx.json",
      "nx/target-defaults"
    ],
    "targets.test.parallelism": [
      "nx.json",
      "nx/target-defaults"
    ]
  },
  ".": {
    "root": [
      "package.json",
      "nx/core/package-json"
    ],
    "targets": [
      "jest.config.ts",
      "@nx/jest/plugin"
    ],
    "targets.test": [
      "jest.config.ts",
      "@nx/jest/plugin"
    ],
    "targets.test.options": [
      "jest.config.ts",
      "@nx/jest/plugin"
    ],
    "targets.test.metadata": [
      "jest.config.ts",
      "@nx/jest/plugin"
    ],
    "targets.test.cache": [
      "jest.config.ts",
      "@nx/jest/plugin"
    ],
    "targets.test.inputs": [
      "jest.config.ts",
      "@nx/jest/plugin"
    ],
    "targets.test.outputs": [
      "jest.config.ts",
      "@nx/jest/plugin"
    ],
    "targets.test.executor": [
      "jest.config.ts",
      "@nx/jest/plugin"
    ],
    "targets.test.options.cwd": [
      "jest.config.ts",
      "@nx/jest/plugin"
    ],
    "targets.test.options.env": [
      "jest.config.ts",
      "@nx/jest/plugin"
    ],
    "targets.test.options.command": [
      "jest.config.ts",
      "@nx/jest/plugin"
    ],
    "targets.test.metadata.technologies": [
      "jest.config.ts",
      "@nx/jest/plugin"
    ],
    "targets.test.metadata.technologies.0": [
      "jest.config.ts",
      "@nx/jest/plugin"
    ],
    "targets.test.metadata.description": [
      "jest.config.ts",
      "@nx/jest/plugin"
    ],
    "targets.test.metadata.help": [
      "jest.config.ts",
      "@nx/jest/plugin"
    ],
    "targets.test.metadata.help.command": [
      "jest.config.ts",
      "@nx/jest/plugin"
    ],
    "targets.test.metadata.help.example": [
      "jest.config.ts",
      "@nx/jest/plugin"
    ],
    "name": [
      "package.json",
      "nx/core/package-json"
    ],
    "includedScripts": [
      "package.json",
      "nx/core/package-json"
    ],
    "tags": [
      "package.json",
      "nx/core/package-json"
    ],
    "tags.npm:private": [
      "package.json",
      "nx/core/package-json"
    ],
    "metadata.targetGroups": [
      "package.json",
      "nx/core/package-json"
    ],
    "metadata.js": [
      "package.json",
      "nx/core/package-json"
    ],
    "metadata.js.packageName": [
      "package.json",
      "nx/core/package-json"
    ],
    "metadata.js.packageVersion": [
      "package.json",
      "nx/core/package-json"
    ],
    "metadata.js.isInPackageManagerWorkspaces": [
      "package.json",
      "nx/core/package-json"
    ],
    "targets.local-registry": [
      "package.json",
      "nx/core/package-json"
    ],
    "targets.local-registry.executor": [
      "package.json",
      "nx/core/package-json"
    ],
    "targets.local-registry.options": [
      "package.json",
      "nx/core/package-json"
    ],
    "targets.local-registry.options.port": [
      "package.json",
      "nx/core/package-json"
    ],
    "targets.local-registry.options.config": [
      "package.json",
      "nx/core/package-json"
    ],
    "targets.local-registry.options.storage": [
      "package.json",
      "nx/core/package-json"
    ],
    "targets.test.dependsOn": [
      "nx.json",
      "nx/target-defaults"
    ],
    "targets.test.parallelism": [
      "nx.json",
      "nx/target-defaults"
    ]
  }
}